howtomathdummythisisatest/__init__.py
howtomathdummythisisatest/mathly.py
howtomathdummythisisatest-0.1.2.dist-info/METADATA
howtomathdummythisisatest-0.1.2.dist-info/WHEEL
howtomathdummythisisatest-0.1.2.dist-info/RECORD
