Metadata-Version: 2.1
Name: howtomathdummythisisatest
Version: 0.1.2
Summary: desp
License: any
Author: deekshith.tirumala
Author-email: deekshith.tirumala@infosys.com
Requires-Python: >=3.12,<4.0
Classifier: License :: Other/Proprietary License
Classifier: Programming Language :: Python :: 3
Classifier: Programming Language :: Python :: 3.12
Classifier: Programming Language :: Python :: 3.13
